gh_stars_export.py
gh_stars_export-0.2.0.dist-info/entry_points.txt
gh_stars_export-0.2.0.dist-info/LICENSE
gh_stars_export-0.2.0.dist-info/WHEEL
gh_stars_export-0.2.0.dist-info/METADATA
gh_stars_export-0.2.0.dist-info/RECORD
