Metadata-Version: 2.1
Name: gh-stars-export
Version: 0.2.0
Summary: This script exports your github stars to a json file.
License: MIT
Author: Ayush Shanker
Author-email: ayushshanker@outlook.in
Requires-Python: >=3.6,<4.0
Classifier: License :: OSI Approved :: MIT License
Classifier: Programming Language :: Python :: 3
Classifier: Programming Language :: Python :: 3.6
Classifier: Programming Language :: Python :: 3.7
Classifier: Programming Language :: Python :: 3.8
Requires-Dist: PyGithub (>=1.5.1,<2.0.0)
